{
    "title": "Drive Medical Parallel Height Adjustable Tub Rail",
    "description": "",
    "referenceId": "1904839404",
    "date_created": "1502524044",
    "date_modified": "1504247457",
    "tags": "",
    "sourceId": "6",
    "VIDEO_LENGTH": "SHORT",
    "video_type": null,
    "status": "approved",
    "visibility": "1",
    "category_id_1": null,
    "category_id_2": null,
    "category_id_3": null,
    "category_id_4": null,
    "category_id_5": null,
    "Concept": null,
    "mod_request": null,
    "cc_request": null,
    "creator": null,
    "video_classification1": null,
    "user_id": null,
    "id": "109996846",
    "loginId": "1758166",
    "entityType": "1",
    "titleTextEncoded": "drive-medical-parallel-height-adjustable-tub-rail",
    "category": "",
    "duration": "84",
    "settings": "",
    "asset": {
        "user": "",
        "videoMeta": {
            "duration": "84",
            "width": 1280,
            "height": 720
        },
        "mediaDuration": "84",
        "prettyDuration": "00:01:24",
        "thumbnailUrl": "\/\/v.tvpage.com\/1758166\/109996846\/bb114\/thumb-7210ea590772ca0d1f821b3d2e4bd21d-00002.jpg",
        "type": "mp4",
        "dashUrl": "\/\/v.tvpage.com\/1758166\/109996846\/bb114\/media.mpd",
        "hlsUrl": "\/\/v.tvpage.com\/1758166\/109996846\/bb114\/media.m3u8",
        "uploadAsset": false,
        "quality": "",
        "sources": [
            {
                "file": "\/\/v.tvpage.com\/1758166\/109996846\/bb114\/1080p_media.mp4",
                "quality": "1080p",
                "mime": "video\/mp4",
                "width": 1280,
                "height": 720
            },
            {
                "file": "\/\/v.tvpage.com\/1758166\/109996846\/bb114\/720p_media.mp4",
                "quality": "720p",
                "mime": "video\/mp4",
                "width": 1280,
                "height": 720
            },
            {
                "file": "\/\/v.tvpage.com\/1758166\/109996846\/bb114\/480p_media.mp4",
                "quality": "480p",
                "mime": "video\/mp4",
                "width": 854,
                "height": 480
            },
            {
                "file": "\/\/v.tvpage.com\/1758166\/109996846\/bb114\/360p_media.mp4",
                "quality": "360p",
                "mime": "video\/mp4",
                "width": 640,
                "height": 360
            },
            {
                "file": "\/\/v.tvpage.com\/1758166\/109996846\/bb114\/240p_media.mp4",
                "quality": "240p",
                "mime": "video\/mp4",
                "width": 320,
                "height": 180
            }
        ],
        "cc": [
            {
                "label": "English",
                "srclang": "en",
                "src": "\/\/v.tvpage.com\/1758166\/109996846\/cc\/vtt\/en_1504225596.vtt",
                "default": true
            }
        ]
    },
    "delete": "",
    "notes": null,
    "uploader": "dnicoletti",
    "modified_date": "12\/16\/2013",
    "created_date": "12\/16\/2013"
}