{
    "title": "Shark Tank Simply Fit Board&reg;",
    "description": "",
    "referenceId": "1530966677",
    "date_created": "1502521272",
    "date_modified": "1504247454",
    "tags": "",
    "sourceId": "6",
    "VIDEO_LENGTH": "SHORT",
    "video_type": null,
    "status": "approved",
    "visibility": "1",
    "category_id_1": null,
    "category_id_2": null,
    "category_id_3": null,
    "category_id_4": null,
    "category_id_5": null,
    "Concept": null,
    "mod_request": null,
    "cc_request": null,
    "creator": null,
    "video_classification1": null,
    "user_id": null,
    "id": "109982800",
    "loginId": "1758166",
    "entityType": "1",
    "titleTextEncoded": "shark-tank-simply-fit-board",
    "category": "",
    "duration": "83",
    "settings": "",
    "asset": {
        "user": "",
        "videoMeta": {
            "duration": "83",
            "width": 1280,
            "height": 720
        },
        "mediaDuration": "83",
        "prettyDuration": "00:01:23",
        "thumbnailUrl": "\/\/v.tvpage.com\/1758166\/109982800\/9ff9b\/thumb-9cc07fc5a9e1a548e8f69bd752299a73-00002.jpg",
        "type": "mp4",
        "dashUrl": "\/\/v.tvpage.com\/1758166\/109982800\/9ff9b\/media.mpd",
        "hlsUrl": "\/\/v.tvpage.com\/1758166\/109982800\/9ff9b\/media.m3u8",
        "uploadAsset": false,
        "quality": "",
        "sources": [
            {
                "file": "\/\/v.tvpage.com\/1758166\/109982800\/9ff9b\/1080p_media.mp4",
                "quality": "1080p",
                "mime": "video\/mp4",
                "width": 1280,
                "height": 720
            },
            {
                "file": "\/\/v.tvpage.com\/1758166\/109982800\/9ff9b\/720p_media.mp4",
                "quality": "720p",
                "mime": "video\/mp4",
                "width": 1280,
                "height": 720
            },
            {
                "file": "\/\/v.tvpage.com\/1758166\/109982800\/9ff9b\/480p_media.mp4",
                "quality": "480p",
                "mime": "video\/mp4",
                "width": 854,
                "height": 480
            },
            {
                "file": "\/\/v.tvpage.com\/1758166\/109982800\/9ff9b\/360p_media.mp4",
                "quality": "360p",
                "mime": "video\/mp4",
                "width": 640,
                "height": 360
            },
            {
                "file": "\/\/v.tvpage.com\/1758166\/109982800\/9ff9b\/240p_media.mp4",
                "quality": "240p",
                "mime": "video\/mp4",
                "width": 320,
                "height": 180
            }
        ],
        "cc": [
            {
                "label": "English",
                "srclang": "en",
                "src": "\/\/v.tvpage.com\/1758166\/109982800\/cc\/vtt\/en_1504135771.vtt",
                "default": true
            }
        ]
    },
    "delete": "",
    "notes": null,
    "uploader": "Douglas.French",
    "modified_date": "7\/24\/2017",
    "created_date": "7\/24\/2017"
}