{
    "title": "Brookstone Automatic Wine Preserver",
    "description": "",
    "referenceId": "1593323779",
    "date_created": "1502521747",
    "date_modified": "1504328404",
    "tags": "",
    "sourceId": "6",
    "VIDEO_LENGTH": "SHORT",
    "video_type": null,
    "status": "approved",
    "visibility": "1",
    "category_id_1": null,
    "category_id_2": null,
    "category_id_3": null,
    "category_id_4": null,
    "category_id_5": null,
    "Concept": null,
    "mod_request": null,
    "cc_request": null,
    "creator": null,
    "video_classification1": null,
    "user_id": null,
    "id": "109983969",
    "loginId": "1758166",
    "entityType": "1",
    "titleTextEncoded": "brookstone-automatic-wine-preserver",
    "category": "",
    "duration": "55",
    "settings": "",
    "asset": {
        "user": "",
        "videoMeta": {
            "duration": "55",
            "width": 640,
            "height": 360
        },
        "mediaDuration": "55",
        "prettyDuration": "00:00:55",
        "thumbnailUrl": "\/\/sitecdn.tvpage.com\/live\/users\/1758166\/canvas\/320\/179\/244949500-01320180.jpg",
        "type": "mp4",
        "dashUrl": "\/\/v.tvpage.com\/1758166\/109983969\/d3e65\/media.mpd",
        "hlsUrl": "\/\/v.tvpage.com\/1758166\/109983969\/d3e65\/media.m3u8",
        "uploadAsset": false,
        "quality": "",
        "cc": [
            {
                "label": "English",
                "srclang": "en",
                "src": "\/\/v.tvpage.com\/1758166\/109983969\/cc\/vtt\/en_1504223345.vtt",
                "default": true
            }
        ],
        "sources": [
            {
                "file": "\/\/v.tvpage.com\/1758166\/109983969\/d3e65\/1080p_media.mp4",
                "quality": "1080p",
                "mime": "video\/mp4",
                "width": 640,
                "height": 360
            },
            {
                "file": "\/\/v.tvpage.com\/1758166\/109983969\/d3e65\/720p_media.mp4",
                "quality": "720p",
                "mime": "video\/mp4",
                "width": 640,
                "height": 360
            },
            {
                "file": "\/\/v.tvpage.com\/1758166\/109983969\/d3e65\/480p_media.mp4",
                "quality": "480p",
                "mime": "video\/mp4",
                "width": 640,
                "height": 360
            },
            {
                "file": "\/\/v.tvpage.com\/1758166\/109983969\/d3e65\/360p_media.mp4",
                "quality": "360p",
                "mime": "video\/mp4",
                "width": 640,
                "height": 360
            },
            {
                "file": "\/\/v.tvpage.com\/1758166\/109983969\/d3e65\/240p_media.mp4",
                "quality": "240p",
                "mime": "video\/mp4",
                "width": 320,
                "height": 180
            }
        ]
    },
    "delete": "",
    "notes": "",
    "uploader": "christina.steel",
    "modified_date": "10\/18\/2013",
    "created_date": "10\/18\/2013"
}