{
    "title": "Biggest Loser Cal-Max Kitchen Scale",
    "description": "",
    "referenceId": "41589",
    "date_created": "1502525062",
    "date_modified": "1504247457",
    "tags": "",
    "sourceId": "6",
    "VIDEO_LENGTH": "SHORT",
    "video_type": null,
    "status": "approved",
    "visibility": "1",
    "category_id_1": null,
    "category_id_2": null,
    "category_id_3": null,
    "category_id_4": null,
    "category_id_5": null,
    "Concept": null,
    "mod_request": null,
    "cc_request": null,
    "creator": null,
    "video_classification1": null,
    "user_id": null,
    "id": "110004213",
    "loginId": "1758166",
    "entityType": "1",
    "titleTextEncoded": "biggest-loser-cal-max-kitchen-scale",
    "category": "",
    "duration": "78",
    "settings": "",
    "asset": {
        "user": "",
        "videoMeta": {
            "duration": "78",
            "width": 640,
            "height": 360
        },
        "mediaDuration": "78",
        "prettyDuration": "00:01:18",
        "thumbnailUrl": "\/\/v.tvpage.com\/1758166\/110004213\/b0150\/thumb-a2b2f9d637d3d8db473721e22de96947-00002.jpg",
        "type": "mp4",
        "dashUrl": "\/\/v.tvpage.com\/1758166\/110004213\/b0150\/media.mpd",
        "hlsUrl": "\/\/v.tvpage.com\/1758166\/110004213\/b0150\/media.m3u8",
        "uploadAsset": false,
        "quality": "",
        "sources": [
            {
                "file": "\/\/v.tvpage.com\/1758166\/110004213\/b0150\/1080p_media.mp4",
                "quality": "1080p",
                "mime": "video\/mp4",
                "width": 640,
                "height": 360
            },
            {
                "file": "\/\/v.tvpage.com\/1758166\/110004213\/b0150\/720p_media.mp4",
                "quality": "720p",
                "mime": "video\/mp4",
                "width": 640,
                "height": 360
            },
            {
                "file": "\/\/v.tvpage.com\/1758166\/110004213\/b0150\/480p_media.mp4",
                "quality": "480p",
                "mime": "video\/mp4",
                "width": 640,
                "height": 360
            },
            {
                "file": "\/\/v.tvpage.com\/1758166\/110004213\/b0150\/360p_media.mp4",
                "quality": "360p",
                "mime": "video\/mp4",
                "width": 640,
                "height": 360
            },
            {
                "file": "\/\/v.tvpage.com\/1758166\/110004213\/b0150\/240p_media.mp4",
                "quality": "240p",
                "mime": "video\/mp4",
                "width": 320,
                "height": 180
            }
        ]
    },
    "delete": "",
    "notes": null,
    "uploader": "amy.gibbons",
    "modified_date": "6\/19\/2013",
    "created_date": "12\/16\/2011"
}