{
    "title": "Kuvings Whole Slow Juicer",
    "description": "For additional information on the featured product please visit: http:\/\/www.surlatable.com\/product\/PRO-2087104\/Kuvings+Whole+Slow+Juicer\n\nDelicious, healthful juicing has never been easier. This masticating slow juicer features an extra-wide feed chute that accommodates an entire apple at once, a burly 240-watt motor and an ultra-strong, slow-rotating screw that pulverizes fruits and vegetables for complete juice extraction. \n\nFor more about Sur La Table, visit www.surlatable.com\n\nSubscribe to our YouTube Channel:\nhttp:\/\/www.youtube.com\/user\/SurLaTableCorp\n\nLike us on Facebook:\nhttps:\/\/www.facebook.com\/surlatable\/\n\nPin us on Pinterest:\nhttp:\/\/pinterest.com\/surlatable\/\n\nFollow us on Twitter:\nhttps:\/\/twitter.com\/Sur_La_Table",
    "referenceId": "ihGF0Nbm26I",
    "date_created": "1435614502",
    "date_modified": "1469735719",
    "tags": "",
    "sourceId": "4",
    "VIDEO_LENGTH": "SHORT",
    "video_type": null,
    "status": "approved",
    "visibility": "1",
    "category_id_1": null,
    "category_id_2": null,
    "category_id_3": null,
    "category_id_4": null,
    "category_id_5": null,
    "Concept": null,
    "mod_request": null,
    "cc_request": null,
    "creator": null,
    "video_classification1": null,
    "user_id": null,
    "id": "67188814",
    "loginId": "1758166",
    "entityType": "1",
    "titleTextEncoded": "Kuvings-Whole-Slow-Juicer",
    "category": "",
    "duration": 138,
    "settings": "",
    "asset": {
        "type": "youtube",
        "thumbnailUrl": "https:\/\/i.ytimg.com\/vi\/ihGF0Nbm26I\/hqdefault.jpg",
        "uploadDate": 1435614502,
        "videoId": "ihGF0Nbm26I",
        "title": "Kuvings Whole Slow Juicer",
        "description": "For additional information on the featured product please visit: http:\/\/www.surlatable.com\/product\/PRO-2087104\/Kuvings+Whole+Slow+Juicer\n\nDelicious, healthful juicing has never been easier. This masticating slow juicer features an extra-wide feed chute that accommodates an entire apple at once, a burly 240-watt motor and an ultra-strong, slow-rotating screw that pulverizes fruits and vegetables for complete juice extraction. \n\nFor more about Sur La Table, visit www.surlatable.com\n\nSubscribe to our YouTube Channel:\nhttp:\/\/www.youtube.com\/user\/SurLaTableCorp\n\nLike us on Facebook:\nhttps:\/\/www.facebook.com\/surlatable\/\n\nPin us on Pinterest:\nhttp:\/\/pinterest.com\/surlatable\/\n\nFollow us on Twitter:\nhttps:\/\/twitter.com\/Sur_La_Table",
        "author": "SurLaTableCorp",
        "mediaDuration": 138,
        "prettyDuration": "00:02:18",
        "views": "601"
    },
    "delete": null,
    "notes": null,
    "uploader": null,
    "modified_date": null,
    "created_date": null
}