{
    "title": "Slice Right - As Seen On TV Watermelon Slicer",
    "description": "Slice Right - As Seen On TV Watermelon Slicer",
    "referenceId": "dgZmOGPQN1Q",
    "date_created": "1469667616",
    "date_modified": "1470087004",
    "tags": null,
    "sourceId": "4",
    "VIDEO_LENGTH": "SHORT",
    "video_type": "timesavers",
    "status": "approved",
    "visibility": "1",
    "category_id_1": null,
    "category_id_2": null,
    "category_id_3": null,
    "category_id_4": null,
    "category_id_5": null,
    "Concept": null,
    "mod_request": null,
    "cc_request": null,
    "creator": null,
    "video_classification1": null,
    "user_id": null,
    "id": "67186114",
    "loginId": "1758166",
    "entityType": "1",
    "titleTextEncoded": "Slice-Right-As-Seen-On-TV-Watermelon-Slicer",
    "category": null,
    "duration": 87,
    "settings": null,
    "asset": {
        "type": "youtube",
        "author": "As Seen On TV & Beyond",
        "hdvFlag": 1,
        "hookText": "Slice Right - As Seen On TV Watermelon Slicer\nBuy it at: http:\/\/www.asseenontvandbeyond.com\/Slice-Right--As-Seen-On-TV-Watermelon-Slicer_p_239.html",
        "tags": "",
        "thumbnailUrl": "https:\/\/i.ytimg.com\/vi\/dgZmOGPQN1Q\/hqdefault.jpg",
        "videoId": "dgZmOGPQN1Q",
        "mediaDuration": 87,
        "prettyDuration": "00:01:27",
        "uploadAsset": false,
        "quality": ""
    },
    "delete": null,
    "notes": null,
    "uploader": null,
    "modified_date": null,
    "created_date": null
}