{
    "title": "OXO Flare Grinders",
    "description": "With stainless steel accents and clear acrylic bodies, the OXO Good Grips Salt Grinder and Pepper Grinder are perfect for cooking in the kitchen and elegantly designed to bring to the table. The Grinders are easily adjustable from fine to coarse grind and rest flat when upside down for easy refilling. Non-corrosive ceramic grinders won't absorb flavors or odors, and are positioned at the top of the Grinders so as not to leave a mess on the counter or table. The Grinders have a soft, non-slip grip for comfortable grinding and are sold filled with sea salt and black peppercorns.",
    "referenceId": "wAQ0VkrZ4EI",
    "date_created": "1383597517",
    "date_modified": "1487206055",
    "tags": "",
    "sourceId": "4",
    "VIDEO_LENGTH": "SHORT",
    "video_type": null,
    "status": "approved",
    "visibility": "1",
    "category_id_1": null,
    "category_id_2": null,
    "category_id_3": null,
    "category_id_4": null,
    "category_id_5": null,
    "Concept": null,
    "mod_request": null,
    "cc_request": null,
    "creator": null,
    "video_classification1": null,
    "user_id": null,
    "id": "7163201",
    "loginId": "1758166",
    "entityType": "1",
    "titleTextEncoded": "OXO-Flare-Grinders",
    "category": "",
    "duration": "58",
    "settings": "",
    "asset": {
        "type": "youtube",
        "thumbnailUrl": "https:\/\/i.ytimg.com\/vi\/wAQ0VkrZ4EI\/hqdefault.jpg",
        "uploadDate": 1383597517,
        "videoId": "wAQ0VkrZ4EI",
        "title": "OXO Flare Grinders",
        "description": "http:\/\/www.oxo.com\/p-497-salt-pepper-grinder-set.aspx\n\nWith stainless steel accents and clear acrylic bodies, the OXO Good Grips Salt Grinder and Pepper Grinder are perfect for cooking in the kitchen and elegantly designed to bring to the table. The Grinders are easily adjustable from fine to coarse grind and rest flat when upside down for easy refilling. Non-corrosive ceramic grinders won't absorb flavors or odors, and are positioned at the top of the Grinders so as not to leave a mess on the counter or table. The Grinders have a soft, non-slip grip for comfortable grinding and are sold filled with sea salt and black peppercorns.",
        "author": "OXO",
        "mediaDuration": "58",
        "prettyDuration": "00:00:58",
        "views": "1008",
        "uploadAsset": false,
        "quality": ""
    },
    "delete": null,
    "notes": null,
    "uploader": null,
    "modified_date": null,
    "created_date": null
}