{
    "title": "Store Containers with Salt to Keep Them Odor Free",
    "description": "Do your storage containers have a lingering odor even after you have washed them thoroughly? Just store them with a pinch of salt to keep them odor free!\n\nHave any good tips?",
    "referenceId": "OYDronQw2NA",
    "date_created": "1425397450",
    "date_modified": "1452200760",
    "tags": "",
    "sourceId": "4",
    "VIDEO_LENGTH": "SHORT",
    "video_type": null,
    "status": "approved",
    "visibility": "1",
    "category_id_1": null,
    "category_id_2": null,
    "category_id_3": null,
    "category_id_4": null,
    "category_id_5": null,
    "Concept": null,
    "mod_request": null,
    "cc_request": null,
    "creator": null,
    "video_classification1": null,
    "user_id": null,
    "id": "7162920",
    "loginId": "1758166",
    "entityType": "1",
    "titleTextEncoded": "Store-Containers-with-Salt-to-Keep-Them-Odor-Free",
    "category": "",
    "duration": "16",
    "settings": "",
    "asset": {
        "type": "youtube",
        "thumbnailUrl": "https:\/\/i.ytimg.com\/vi\/OYDronQw2NA\/hqdefault.jpg",
        "uploadDate": 1425397450,
        "videoId": "OYDronQw2NA",
        "title": "Store Containers with Salt to Keep Them Odor Free",
        "description": "Do your storage containers have a lingering odor even after you have washed them thoroughly? Just store them with a pinch of salt to keep them odor free!\n\nHave any good tips? Share them with us on Twitter and Instagram using the hashtag #OXOGoodTips.\n\nHave questions or comments? Here's where you can find us:\n\nhttp:\/\/facebook.com\/oxo\nhttp:\/\/twitter.com\/oxo\nhttp:\/\/pinterest.com\/oxo\nhttp:\/\/instagram.com\/oxo",
        "author": "OXO",
        "mediaDuration": "16",
        "prettyDuration": "00:00:16",
        "views": "952"
    },
    "delete": null,
    "notes": null,
    "uploader": null,
    "modified_date": null,
    "created_date": null
}