{
    "title": "Char-Broil Memorial Day Cookout",
    "description": "This past Memorial Day, we cooked out on the Char-Broil deck for our hungry sales staff. Ladon Hopkins grilled some sliders, brats, potatoes, and onions on two infrared grills: The Char-Broil RED Urban 2-burner grill and the Char-Broil Electric Patio Bistro.",
    "referenceId": "ceKP1maF6yc",
    "date_created": "1306956960",
    "date_modified": "1491522515",
    "tags": "",
    "sourceId": "4",
    "VIDEO_LENGTH": "LONG",
    "video_type": "outdoor_living",
    "status": "approved",
    "visibility": "1",
    "category_id_1": null,
    "category_id_2": null,
    "category_id_3": null,
    "category_id_4": null,
    "category_id_5": null,
    "Concept": null,
    "mod_request": null,
    "cc_request": null,
    "creator": null,
    "video_classification1": null,
    "user_id": null,
    "id": "7163937",
    "loginId": "1758166",
    "entityType": "1",
    "titleTextEncoded": "Char-Broil-Memorial-Day-Cookout",
    "category": "",
    "duration": 10000,
    "settings": {},
    "asset": {
        "type": "youtube",
        "thumbnailUrl": "https:\/\/i.ytimg.com\/vi\/ceKP1maF6yc\/hqdefault.jpg",
        "uploadDate": 1306956960,
        "videoId": "ceKP1maF6yc",
        "title": "Char-Broil Memorial Day Cookout",
        "description": "This past Memorial Day, we cooked out on the Char-Broil deck for our hungry sales staff. Ladon Hopkins grilled some sliders, brats, potatoes, and onions on two infrared grills: The Char-Broil RED Urban 2-burner grill and the Char-Broil Electric Patio Bistro.",
        "author": "Char-Broil Grills",
        "mediaDuration": "99",
        "prettyDuration": "00:01:39",
        "views": "813",
        "uploadAsset": false,
        "quality": ""
    },
    "delete": null,
    "notes": null,
    "uploader": null,
    "modified_date": null,
    "created_date": null
}