{
    "title": "AG Sprout Black LED 30Day TL",
    "description": "Sprout 30 Day Time Lapse",
    "referenceId": "sCPusnn4TjQ",
    "date_created": "1488322886",
    "date_modified": "1491355589",
    "tags": null,
    "sourceId": "4",
    "VIDEO_LENGTH": "SHORT",
    "video_type": "Gardening",
    "status": "approved",
    "visibility": "1",
    "category_id_1": null,
    "category_id_2": null,
    "category_id_3": null,
    "category_id_4": null,
    "category_id_5": null,
    "Concept": null,
    "mod_request": null,
    "cc_request": null,
    "creator": null,
    "video_classification1": null,
    "user_id": null,
    "id": "85591148",
    "loginId": "1758166",
    "entityType": "1",
    "titleTextEncoded": "AG-Sprout-Black-LED-30Day-TL",
    "category": null,
    "duration": 10,
    "settings": null,
    "asset": {
        "type": "youtube",
        "author": "Miracle-Gro AeroGarden",
        "hdvFlag": 1,
        "description": "Sprout 30 Day Time Lapse http:\/\/www.aerogarden.com\/",
        "tags": "",
        "thumbnailUrl": "https:\/\/i.ytimg.com\/vi\/sCPusnn4TjQ\/hqdefault.jpg",
        "videoId": "sCPusnn4TjQ",
        "mediaDuration": 10,
        "prettyDuration": "00:00:10",
        "uploadAsset": false,
        "quality": ""
    },
    "delete": null,
    "notes": null,
    "uploader": null,
    "modified_date": null,
    "created_date": null
}